flask_inspektor/__init__.py
flask_inspektor/extension.py
flask_inspektor-0.1.1.dist-info/LICENSE
flask_inspektor-0.1.1.dist-info/METADATA
flask_inspektor-0.1.1.dist-info/WHEEL
flask_inspektor-0.1.1.dist-info/top_level.txt
flask_inspektor-0.1.1.dist-info/RECORD
