Metadata-Version: 2.1
Name: flask-inspektor
Version: 0.1.1
Summary: SQLAlchemy querying metrics collection and reporting extension for Flask.
Home-page: https://github.com/getbyrd/inspektor
Author: Byrd Technologies GmbH
Author-email: developers@getbyrd.com
License: MIT
Platform: UNKNOWN
Classifier: Development Status :: 5 - Production/Stable
Classifier: Intended Audience :: Developers
Classifier: License :: OSI Approved :: MIT License
Classifier: Operating System :: Unix
Classifier: Operating System :: POSIX
Classifier: Programming Language :: Python
Classifier: Programming Language :: Python :: 2
Classifier: Programming Language :: Python :: 2.7
Classifier: Programming Language :: Python :: 3
Classifier: Programming Language :: Python :: 3.6
Classifier: Programming Language :: Python :: 3.7
Classifier: Programming Language :: Python :: Implementation :: CPython
Classifier: Topic :: Software Development :: Libraries :: Python Modules
Classifier: Environment :: Web Environment
Requires-Python: >=2.7, !=3.0.*, !=3.1.*, !=3.2.*, !=3.3.*
Requires-Dist: flask (>=1.0)
Requires-Dist: future (>=0.16.0)
Requires-Dist: SQLAlchemy (>=1.2.2)
Provides-Extra: dev
Requires-Dist: Flask-SQLAlchemy (<2.5.0,>=2.4.0) ; extra == 'dev'
Requires-Dist: flask-testing (>=0.7.1) ; extra == 'dev'
Requires-Dist: pytest (>=4.6.0) ; extra == 'dev'
Requires-Dist: twine ; extra == 'dev'
Provides-Extra: test
Requires-Dist: Flask-SQLAlchemy (<2.5.0,>=2.4.0) ; extra == 'test'
Requires-Dist: flask-testing (>=0.7.1) ; extra == 'test'
Requires-Dist: pytest (>=4.6.0) ; extra == 'test'
